fwa/__init__.py
fwa/create_app.py
fwa/setup.sh
fwa-0.2.0.dist-info/LICENSE
fwa-0.2.0.dist-info/METADATA
fwa-0.2.0.dist-info/WHEEL
fwa-0.2.0.dist-info/entry_points.txt
fwa-0.2.0.dist-info/RECORD
