Metadata-Version: 2.1
Name: fwa
Version: 0.2.0
Summary: Firefox Web Apps
Home-page: https://gitlab.com/ceda_ei/firefox-web-apps/
License: GPL-3.0-only
Author: Ceda EI
Author-email: ceda_ei@webionite.com
Requires-Python: >=3.8,<4.0
Classifier: Development Status :: 4 - Beta
Classifier: Intended Audience :: End Users/Desktop
Classifier: License :: OSI Approved :: GNU General Public License v3 (GPLv3)
Classifier: Operating System :: POSIX :: Linux
Classifier: Programming Language :: Python :: 3
Classifier: Programming Language :: Python :: 3.8
Classifier: Programming Language :: Python :: 3.9
Classifier: Programming Language :: Python :: 3.10
Classifier: Programming Language :: Python :: 3.11
Classifier: Topic :: Internet
Requires-Dist: beautifulsoup4 (>=4.12.2,<5.0.0)
Requires-Dist: pillow (>=10.0.0,<11.0.0)
Requires-Dist: requests (>=2.31.0,<3.0.0)
Project-URL: Repository, https://gitlab.com/ceda_ei/firefox-web-apps/
